redis_extending_lock/__init__.py
redis_extending_lock-1.0.4.dist-info/LICENSE
redis_extending_lock-1.0.4.dist-info/METADATA
redis_extending_lock-1.0.4.dist-info/WHEEL
redis_extending_lock-1.0.4.dist-info/RECORD
